<?xml version="1.0" encoding="utf-8" ?><dwsync><file name="AntykwaBold.ttf" server="ftp.voyagewaimea.com" local="3521991900" remote="3521991900" Dst="-1" /><file name="Candice.ttf" server="ftp.voyagewaimea.com" local="3521991900" remote="3521991900" Dst="-1" /><file name="Ding-DongDaddyO.ttf" server="ftp.voyagewaimea.com" local="3521991900" remote="3521991900" Dst="-1" /><file name="Duality.ttf" server="ftp.voyagewaimea.com" local="3521991900" remote="3521991900" Dst="-1" /><file name="Heineken.ttf" server="ftp.voyagewaimea.com" local="3521991900" remote="3521991900" Dst="-1" /><file name="Jura.ttf" server="ftp.voyagewaimea.com" local="3521991900" remote="3521991900" Dst="-1" /><file name="StayPuft.ttf" server="ftp.voyagewaimea.com" local="3521991900" remote="3521991900" Dst="-1" /><file name="VeraSansBold.ttf" server="ftp.voyagewaimea.com" local="3521991900" remote="3521991900" Dst="-1" /><file name="TimesNewRomanBold.ttf" server="ftp.voyagewaimea.com" local="3521991900" remote="3521991900" Dst="-1" /></dwsync>