<?xml version="1.0" encoding="utf-8" ?><dwsync><file name=".DS_Store" server="ftp.voyagewaimea.com" local="3520901657" remote="3521589840" Dst="-1" /><file name="about_us.html" server="ftp.voyagewaimea.com" local="3525309866" remote="3525302880" Dst="-1" /><file name="accordion-toggles.html" server="ftp.voyagewaimea.com" local="3521990700" remote="3521990700" Dst="-1" /><file name="buttons.html" server="ftp.voyagewaimea.com" local="3521990700" remote="3521990700" Dst="-1" /><file name="contact.html" server="ftp.voyagewaimea.com" local="3525309866" remote="3525302880" Dst="-1" /><file name="contact.php" server="ftp.voyagewaimea.com" local="3524825489" remote="3524818320" Dst="-1" /><file name="dropcaps.html" server="ftp.voyagewaimea.com" local="3521990700" remote="3521990700" Dst="-1" /><file name="events.html" server="ftp.voyagewaimea.com" local="3525309924" remote="3525302880" Dst="-1" /><file name="faq.html" server="ftp.voyagewaimea.com" local="3525309698" remote="3525302880" Dst="-1" /><file name="images.html" server="ftp.voyagewaimea.com" local="3521991840" remote="3521991840" Dst="-1" /><file name="index.html" server="ftp.voyagewaimea.com" local="3530550239" remote="3530546700" Dst="-1" /><file name="narrative.html" server="ftp.voyagewaimea.com" local="3525309866" remote="3525302880" Dst="-1" /><file name="tabs.html" server="ftp.voyagewaimea.com" local="3521991900" remote="3521991900" Dst="-1" /><file name="the_gospel.html" server="ftp.voyagewaimea.com" local="3525309861" remote="3525302880" Dst="-1" /><file name="what_is_voyage.html" server="ftp.voyagewaimea.com" local="3521991960" remote="3521991960" Dst="-1" /><file name=".ftpquota" server="ftp.voyagewaimea.com" local="3524163540" remote="3524163540" Dst="-1" /><file name="podcast.html" server="ftp.voyagewaimea.com" local="3523224109" remote="3523217040" Dst="-1" /></dwsync>