<?xml version="1.0" encoding="utf-8" ?><dwsync><file name="ava.jpg" server="ftp.voyagewaimea.com" local="3521990880" remote="3521990880" Dst="-1" /><file name="bg_play_pause.png" server="ftp.voyagewaimea.com" local="3521990880" remote="3521990880" Dst="-1" /><file name="background.jpg" server="ftp.voyagewaimea.com" local="3521990880" remote="3521990880" Dst="-1" /><file name="camera-loader.gif" server="ftp.voyagewaimea.com" local="3521986500" remote="3521986500" Dst="-1" /><file name="camera_skins.png" server="ftp.voyagewaimea.com" local="3521986500" remote="3521986500" Dst="-1" /><file name="loader-alt.gif" server="ftp.voyagewaimea.com" local="3521991660" remote="3521991660" Dst="-1" /><file name="logo.png" server="ftp.voyagewaimea.com" local="3521991660" remote="3521991660" Dst="-1" /><file name="nextArrow.png" server="ftp.voyagewaimea.com" local="3521986500" remote="3521986500" Dst="-1" /><file name="office.jpg" server="ftp.voyagewaimea.com" local="3521991660" remote="3521991660" Dst="-1" /><file name="photo.jpg" server="ftp.voyagewaimea.com" local="3521991660" remote="3521991660" Dst="-1" /><file name="preloader.gif" server="ftp.voyagewaimea.com" local="3521991720" remote="3521991720" Dst="-1" /><file name="prevArrow.png" server="ftp.voyagewaimea.com" local="3521986500" remote="3521986500" Dst="-1" /><file name="quote.png" server="ftp.voyagewaimea.com" local="3521986500" remote="3521986500" Dst="-1" /><file name="refresh.png" server="ftp.voyagewaimea.com" local="3521988900" remote="3521988900" Dst="-1" /><file name="responsive.png" server="ftp.voyagewaimea.com" local="3521991720" remote="3521991720" Dst="-1" /><file name="testimonial-arrow.png" server="ftp.voyagewaimea.com" local="3521986500" remote="3521986500" Dst="-1" /><file name="Voyage.jpg" server="ftp.voyagewaimea.com" local="3521986560" remote="3521986560" Dst="-1" /><file name="Voyage.png" server="ftp.voyagewaimea.com" local="3521991780" remote="3521991780" Dst="-1" /><file name="Voyage.psd" server="ftp.voyagewaimea.com" local="3521991840" remote="3521991840" Dst="-1" /><file name="Welcome.jpg" server="ftp.voyagewaimea.com" local="3521991840" remote="3530545800" Dst="-1" /><file name="Hills.jpg" server="ftp.voyagewaimea.com" local="3521991660" remote="3530545800" Dst="-1" /><file name="Enter.jpg" server="ftp.voyagewaimea.com" local="3521991600" remote="3530545800" Dst="-1" /><file name="01DSC_1009.JPG" server="ftp.voyagewaimea.com" local="3521990820" remote="3521990820" Dst="-1" /><file name="02DSC_1011.JPG" server="ftp.voyagewaimea.com" local="3521990820" remote="3521990820" Dst="-1" /><file name="03DSC_1010.JPG" server="ftp.voyagewaimea.com" local="3521990820" remote="3521990820" Dst="-1" /><file name="04DSC_1021.JPG" server="ftp.voyagewaimea.com" local="3521990880" remote="3521990880" Dst="-1" /><file name="DSC_1013.JPG" server="ftp.voyagewaimea.com" local="3521991480" remote="3521991480" Dst="-1" /><file name="DSC_1019.JPG" server="ftp.voyagewaimea.com" local="3521991480" remote="3521991480" Dst="-1" /><file name="DSC_1024.JPG" server="ftp.voyagewaimea.com" local="3521991540" remote="3521991540" Dst="-1" /><file name="DSC_1025.JPG" server="ftp.voyagewaimea.com" local="3521991540" remote="3521991540" Dst="-1" /><file name="Enter.JPG" server="ftp.voyagewaimea.com" local="3521991600" remote="3521991600" Dst="-1" /><file name="Hills.JPG" server="ftp.voyagewaimea.com" local="3521991660" remote="3521991660" Dst="-1" /><file name="Welcome.JPG" server="ftp.voyagewaimea.com" local="3521991840" remote="3521991840" Dst="-1" /><file name="launch_day.jpg" server="ftp.voyagewaimea.com" local="3523221660" remote="3523221660" Dst="-1" /></dwsync>